hanimetvdl/__init__.py
hanimetvdl/api.py
hanimetvdl/cli.py
hanimetvdl-0.0.1.dist-info/METADATA
hanimetvdl-0.0.1.dist-info/WHEEL
hanimetvdl-0.0.1.dist-info/entry_points.txt
hanimetvdl-0.0.1.dist-info/RECORD
