Metadata-Version: 2.1
Name: hanimetvdl
Version: 0.0.1
Summary: Hanime.tv cli dl
Author: pr13260
Author-email: pr1360-noreply@github.com
Requires-Python: >=3.10,<4.0
Classifier: Programming Language :: Python :: 3
Classifier: Programming Language :: Python :: 3.10
Classifier: Programming Language :: Python :: 3.11
Classifier: Programming Language :: Python :: 3.12
Requires-Dist: requests (>=2.32.3,<3.0.0)
Requires-Dist: yt-dlp (>=2024.9.27,<2025.0.0)
